PRPConnector/Connector.py
PRPConnector/TestPRPConnector.py
PRPConnector/__init__.py
PRPConnector-1.1.dist-info/LICENSE
PRPConnector-1.1.dist-info/METADATA
PRPConnector-1.1.dist-info/WHEEL
PRPConnector-1.1.dist-info/top_level.txt
PRPConnector-1.1.dist-info/RECORD
