Metadata-Version: 2.1
Name: PRPConnector
Version: 1.1
Summary: Connector for Clients to the PRP-Backend
Home-page: https://github.com/manuelbieri/PRP-APIConnect
Author: Manuel Bieri
Author-email: marbl.ch@outlook.com
License: MIT
Download-URL: https://github.com/manuelbieri/PRP-APIConnect/archive/refs/tags/v1.0.tar.gz
Keywords: API
Platform: UNKNOWN
Classifier: Development Status :: 4 - Beta
Classifier: Intended Audience :: Developers
Classifier: Topic :: Software Development
Classifier: License :: OSI Approved :: MIT License
Classifier: Programming Language :: Python :: 3
Classifier: Programming Language :: Python :: 3.6
Classifier: Programming Language :: Python :: 3.7
Classifier: Programming Language :: Python :: 3.8
License-File: LICENSE
